asyncio_cancel_scope/__init__.py
asyncio_cancel_scope/core.py
asyncio_cancel_scope/py.typed
asyncio_cancel_scope-0.3.0.dist-info/METADATA
asyncio_cancel_scope-0.3.0.dist-info/WHEEL
asyncio_cancel_scope-0.3.0.dist-info/licenses/LICENSE.txt
asyncio_cancel_scope-0.3.0.dist-info/RECORD
