Metadata-Version: 2.4
Name: asyncio_cancel_scope
Version: 0.3.0
Summary: A utility for cancelling asyncio task groups.
Project-URL: Source, https://github.com/rmorshea/asyncio-cancel-scope
Author-email: Ryan Morshead <ryan.morshead@gmail.com>
License: MIT License
License-File: LICENSE.txt
Classifier: Development Status :: 4 - Beta
Classifier: Programming Language :: Python
Requires-Python: <4,>=3.11
